{
  "resourceType" : "ValueSet",
  "id" : "fr-current-medication-document-type",
  "meta" : {
    "profile" : ["http://hl7.org/fhir/StructureDefinition/shareablevalueset"]
  },
  "text" : {
    "status" : "generated",
    "div" : "<div xmlns=\"http://www.w3.org/1999/xhtml\"><p class=\"res-header-id\"><b>Generated Narrative: ValueSet fr-current-medication-document-type</b></p><a name=\"fr-current-medication-document-type\"> </a><a name=\"hcfr-current-medication-document-type\"> </a><a name=\"fr-current-medication-document-type-en-US\"> </a><ul><li>Include codes from<a href=\"CodeSystem-fr-document-type.html\"><code>https://hl7.fr/fhir/fr/medication/CodeSystem/fr-document-type</code></a> where isCurrentMedication  = true</li></ul></div>"
  },
  "url" : "https://hl7.fr/fhir/fr/medication/ValueSet/fr-current-medication-document-type",
  "version" : "0.1.0",
  "name" : "FrCurrentMedicationDocumentType",
  "title" : "value set Interop'Santé - type de document de la ressource Composition d'une FCT",
  "status" : "draft",
  "experimental" : false,
  "date" : "2025-01-07T16:15:18+00:00",
  "publisher" : "Interop'Santé",
  "contact" : [{
    "name" : "Interop'Santé",
    "telecom" : [{
      "system" : "url",
      "value" : "http://interopsante.org/"
    }]
  }],
  "description" : "Le jeu de valeurs à utiliser pour coder le type de document de la ressource *Composition* d'une liste des Traitements Médicamenteux Courants.",
  "immutable" : false,
  "compose" : {
    "include" : [{
      "system" : "https://hl7.fr/fhir/fr/medication/CodeSystem/fr-document-type",
      "filter" : [{
        "property" : "isCurrentMedication",
        "op" : "=",
        "value" : "true"
      }]
    }]
  }
}